{
  "school": "인천과학예술영재학교",
  "built_at_kst": "2026-03-24 05:54:23",
  "meals": {
    "today": {
      "date": "20260324",
      "1": [
        "찹쌀밥",
        "크로플",
        "누룽지(자율)",
        "짬뽕국_",
        "데리야끼훈제오리",
        "배추김치",
        "우유/시리얼",
        "두유/검은콩두유",
        "과일(파인애플)"
      ],
      "2": [
        "차조밥",
        "시락국",
        "매운돼지갈비찜(중식)",
        "콩나물무침(중식)",
        "팽이버섯전(오븐)(중식)",
        "깍두기",
        "오렌지컵"
      ],
      "3": [
        "찹쌀밥",
        "계란파국(석)",
        "망고샐러드(석)",
        "토마토치킨커리(석)",
        "탄두리치킨(석)",
        "배추김치",
        "망고라씨"
      ]
    },
    "tomorrow": {
      "date": "20260325",
      "1": [
        "참치마요덮밥",
        "크라운빵",
        "누룽지(자율)",
        "얼큰소고기무국_",
        "배추김치",
        "우유/시리얼",
        "과일(사과)",
        "두유/검은콩두유"
      ]
    }
  }
}