{
  "school": "인천과학예술영재학교",
  "built_at_kst": "2026-04-30 15:12:08",
  "meals": {
    "today": {
      "date": "20260430",
      "1": [
        "주꾸미덮밥_",
        "누룽지(자율)",
        "순두부계란탕_",
        "배추김치",
        "치즈모닝소금빵",
        "두유/검은콩두유",
        "우유/시리얼",
        "과일(바나나)"
      ],
      "2": [
        "차조밥(고)",
        "시트러스샐러드(중식)",
        "차슈",
        "배추김치",
        "단무지무침",
        "타코야끼",
        "돈코츠라멘"
      ],
      "3": []
    },
    "tomorrow": {
      "date": "20260501",
      "1": []
    }
  }
}