{
  "school": "인천과학예술영재학교",
  "built_at_kst": "2025-11-22 12:45:08",
  "meals": {
    "today": {
      "date": "20251122",
      "1": [
        "발아현미밥",
        "붓세",
        "누룽지(자율)",
        "김치찌개(돈육)_",
        "닭살카레볶음",
        "총각김치(완)",
        "우유/시리얼",
        "두유/검은콩두유",
        "과일(사과)"
      ],
      "2": [
        "혼합잡곡밥",
        "조랭이떡국+떡국장",
        "어향가지튀김",
        "고추장오리불고기(중식)",
        "배추김치",
        "프링글스"
      ],
      "3": [
        "깍두기볶음밥(석)",
        "사골미역국",
        "양상추에그마요샐러드(석)",
        "등심돈까스(오븐)/소스",
        "야채모둠피클",
        "배추김치"
      ]
    },
    "tomorrow": {
      "date": "20251123",
      "1": [
        "찹쌀밥",
        "햄김치볶음",
        "호두파운드케이크",
        "누룽지(자율)",
        "새우무국_",
        "깍두기",
        "우유/시리얼",
        "두유/검은콩두유",
        "과일(블루베리)"
      ]
    }
  }
}