{
  "school": "인천과학예술영재학교",
  "built_at_kst": "2026-04-23 10:11:54",
  "meals": {
    "today": {
      "date": "20260423",
      "1": [
        "마들렌",
        "누룽지(자율)",
        "계란떡국",
        "눈꽃제육덮밥",
        "깍두기(고)",
        "두유/검은콩두유",
        "우유/시리얼",
        "과일(꿀자몽)"
      ],
      "2": [
        "시험뿌셔(과자)",
        "취나물밥",
        "메밀전병",
        "배추김치",
        "미나리양념장(밥)",
        "매운등갈비찜",
        "야채된장찌개"
      ],
      "3": [
        "해물볶음밥(석)",
        "바움쿠헨",
        "김치콩나물국",
        "닭감자조림(석)",
        "양상추에그마요샐러드(석)",
        "배추김치"
      ]
    },
    "tomorrow": {
      "date": "20260424",
      "1": [
        "찹쌀밥(고)",
        "대게살야채죽_",
        "플라워파이",
        "누룽지(자율)",
        "돈육메추리알장조림",
        "깍두기(고)",
        "두유/검은콩두유",
        "과일(오렌지)",
        "우유/시리얼"
      ]
    }
  }
}